tmdeploy/__init__.py
tmdeploy/config.py
tmdeploy/errors.py
tmdeploy/inventory.py
tmdeploy/log.py
tmdeploy/utils.py
tmdeploy/version.py
tmdeploy/share/container/images/base/Dockerfile
tmdeploy/share/container/images/base/README.md
tmdeploy/share/container/projects/tissuemaps/docker-compose.local_override.yml
tmdeploy/share/container/projects/tissuemaps/ansible/ansible.cfg
tmdeploy/share/container/projects/tissuemaps/ansible/container.yml
tmdeploy/share/container/projects/tissuemaps/ansible/main.yml
tmdeploy/share/container/projects/tissuemaps/ansible/requirements.txt
tmdeploy/share/container/projects/tissuemaps/ansible/requirements.yml
tmdeploy/share/container/projects/tissuemaps/meta/main.yml
tmdeploy/share/playbooks/elasticluster/ansible.cfg
tmdeploy/share/playbooks/elasticluster/site.yml
tmdeploy/share/playbooks/elasticluster/group_vars/all
tmdeploy/share/playbooks/elasticluster/group_vars/jenkins
tmdeploy/share/playbooks/elasticluster/library/ceph_facts
tmdeploy/share/playbooks/elasticluster/library/drbd
tmdeploy/share/playbooks/elasticluster/library/drbd_sh
tmdeploy/share/playbooks/elasticluster/library/nfsexport
tmdeploy/share/playbooks/elasticluster/roles/ganglia.yml
tmdeploy/share/playbooks/elasticluster/roles/glusterfs.yml
tmdeploy/share/playbooks/elasticluster/roles/slurm.yml
tmdeploy/share/playbooks/elasticluster/roles/cluster/tasks/packages.yml
tmdeploy/share/playbooks/elasticluster/roles/common/files/etc/policy-rc.d
tmdeploy/share/playbooks/elasticluster/roles/common/files/etc/yum.repos.d/gc3.repo.j2
tmdeploy/share/playbooks/elasticluster/roles/common/handlers/main.yml
tmdeploy/share/playbooks/elasticluster/roles/common/tasks/gc3repo.yml
tmdeploy/share/playbooks/elasticluster/roles/common/tasks/hostname.yml
tmdeploy/share/playbooks/elasticluster/roles/common/tasks/hosts.yml
tmdeploy/share/playbooks/elasticluster/roles/common/tasks/init-Debian.yml
tmdeploy-0.3.3.dist-info/DESCRIPTION.rst
tmdeploy-0.3.3.dist-info/METADATA
tmdeploy-0.3.3.dist-info/RECORD
tmdeploy-0.3.3.dist-info/WHEEL
tmdeploy-0.3.3.dist-info/metadata.json
tmdeploy-0.3.3.dist-info/pbr.json
tmdeploy-0.3.3.dist-info/top_level.txt
