Metadata-Version: 2.0
Name: tmdeploy
Version: 0.3.3
Summary: TissueMAPS deployment in virtual environments.
Home-page: https://github.com/tissuemaps/tmdeploy
Author: Markus D. Herrmann
Author-email: UNKNOWN
License: GPL-3.0+
Platform: Linux
Platform: MacOSX
Classifier: Intended Audience :: Developers
Classifier: Intended Audience :: Science/Research
Classifier: Intended Audience :: System Administrators
Classifier: Programming Language :: Python
Classifier: Programming Language :: Python :: 2
Classifier: Programming Language :: Python :: 2.7
Classifier: Programming Language :: Python :: 3
Classifier: Programming Language :: Unix Shell
Classifier: Development Status :: 4 - Beta
Classifier: Operating System :: POSIX :: Linux
Classifier: Operating System :: MacOS
Classifier: Environment :: Console
Classifier: Topic :: Scientific/Engineering
Classifier: Topic :: System :: Clustering
Classifier: Topic :: System :: Distributed Computing
Classifier: Topic :: System :: Software Distribution
Classifier: License :: OSI Approved :: GNU General Public License v3 or later (GPLv3+)
Requires-Dist: PyYAML (>=3.11)
Requires-Dist: ansible (>=2.2.1)
Requires-Dist: apache-libcloud (>=1.3.0)
Requires-Dist: boto (>=2.48)
Requires-Dist: boto3 (>=1.4.1)
Requires-Dist: psycopg2 (>=2.6.1)
Requires-Dist: shade (>=1.12.1)
Requires-Dist: whichcraft (>=0.4.0)
Provides-Extra: container
Requires-Dist: ansible-container (>=0.3.0,<=0.4); extra == 'container'
Requires-Dist: docker-py (>=1.10.6); extra == 'container'
